pychanneldock/__init__.py
pychanneldock/channeldock_api/__init__.py
pychanneldock/channeldock_api/center.py
pychanneldock/channeldock_api/seller.py
pychanneldock/constants/__init__.py
pychanneldock/constants/center_constants.py
pychanneldock/constants/seller_constants.py
pychanneldock-0.3.3.dist-info/LICENSE
pychanneldock-0.3.3.dist-info/METADATA
pychanneldock-0.3.3.dist-info/WHEEL
pychanneldock-0.3.3.dist-info/top_level.txt
pychanneldock-0.3.3.dist-info/RECORD
